yallhap/__init__.py
yallhap/ancient.py
yallhap/bam.py
yallhap/bayesian.py
yallhap/classifier.py
yallhap/cli.py
yallhap/contamination.py
yallhap/isogg.py
yallhap/py.typed
yallhap/scoring.py
yallhap/snps.py
yallhap/tree.py
yallhap/validation.py
yallhap/vcf.py
yallhap-1.0.1.dist-info/licenses/LICENSE
yallhap-1.0.1.dist-info/METADATA
yallhap-1.0.1.dist-info/WHEEL
yallhap-1.0.1.dist-info/entry_points.txt
yallhap-1.0.1.dist-info/top_level.txt
yallhap-1.0.1.dist-info/RECORD
