Metadata-Version: 2.4
Name: yallhap
Version: 1.0.1
Summary: Modern, pipeline-friendly Y-chromosome haplogroup inference
Author: yallHap Contributors
License: PolyForm Noncommercial 1.0.0
Project-URL: Homepage, https://github.com/trianglegrrl/yallhap
Project-URL: Documentation, https://github.com/trianglegrrl/yallhap#readme
Project-URL: Repository, https://github.com/trianglegrrl/yallhap
Project-URL: Issues, https://github.com/trianglegrrl/yallhap/issues
Keywords: bioinformatics,genetics,Y-chromosome,haplogroup,phylogenetics
Classifier: Development Status :: 4 - Beta
Classifier: Environment :: Console
Classifier: Intended Audience :: Science/Research
Classifier: License :: Other/Proprietary License
Classifier: Operating System :: POSIX :: Linux
Classifier: Operating System :: MacOS
Classifier: Programming Language :: Python :: 3
Classifier: Programming Language :: Python :: 3.10
Classifier: Programming Language :: Python :: 3.11
Classifier: Programming Language :: Python :: 3.12
Classifier: Topic :: Scientific/Engineering :: Bio-Informatics
Requires-Python: >=3.10
License-File: LICENSE
Requires-Dist: pysam>=0.22.0
Requires-Dist: pandas>=2.0.0
Requires-Dist: numpy>=1.24.0
Requires-Dist: click>=8.0.0
Requires-Dist: requests>=2.28.0
Requires-Dist: pyliftover>=0.4
Provides-Extra: dev
Requires-Dist: pytest>=7.0.0; extra == "dev"
Requires-Dist: pytest-cov>=4.0.0; extra == "dev"
Requires-Dist: pytest-xdist>=3.0.0; extra == "dev"
Requires-Dist: black>=23.0.0; extra == "dev"
Requires-Dist: ruff>=0.1.0; extra == "dev"
Requires-Dist: mypy>=1.0.0; extra == "dev"
Requires-Dist: pandas-stubs>=2.0.0; extra == "dev"
Requires-Dist: types-requests>=2.28.0; extra == "dev"
Requires-Dist: tqdm>=4.65.0; extra == "dev"
Requires-Dist: rich>=13.0.0; extra == "dev"
Requires-Dist: matplotlib>=3.7.0; extra == "dev"
Dynamic: license-file
